actividad10/mux21.v
`timescale 1ns/1ns

module mux21(
    input [31:0]A,
    input [31:0]B,
    input sel,
    output reg[31:0]R//C
    );
    
always @*
begin

    case(sel)
    1'b1:
    begin
        R = A;
    end

    1'b0:
    begin
        R = B;
    end

    endcase

end

endmodule

actividad10/Mem.v
module Mem(
    input [31:0]Adress,
    input EWR,//c
    input[31:0]WD,
    output reg [31:0]ReadData//c
);
reg [31:0]mem [0:31];

  
always@*
begin
  if(EWR==1'b1)
    begin 
        mem[Adress]=WD;
    end
  else
    begin
      ReadData=mem[Adress];
    end
end


endmodule

actividad10/Alu.v
module Alu(
   input [31:0]op1,
   input [31:0]op2,
   input [2:0]sel,
   output reg[31:0]res,//C
   output reg zeroflag
);
   
always @*
 begin
     case(sel)
     3'b000:
     begin
        res=op1+op2;
     end
     3'b001:
     begin
        res =op1-op2;
     end
     3'b011:
     begin
        res=op1*op2;
     end
     3'b100:
     begin
        res=op1/op2;
     end
     3'b101:
     begin
        res = op1 & op2;
     end
     3'b111:
     begin
        res = op1 | op2;
     end
     3'b110:
     begin
        res = op1<<1;
     end
     3'b010:
     begin
        res = op1<op2?1:0; //op1 ^ op2;
     end
     endcase
zeroflag<=(!res)? 0 : 1;
    
end
endmodule

actividad10/AluC.v
`timescale 1ns/1ns

module AluC(
    input [5:0]func,
    input [2:0]AluOp,
    output reg[2:0]sel
);

always @*
begin
    case(AluOp)
    3'b111:
    begin
        case(func)
        100000://add
        begin   
            sel=3'b000;
        end
        100100://and
        begin
            sel=3'b101;
        end
        100010://sub
        begin
            sel=3'b001;
        end
        100101://or
        begin
            sel=3'b111;
        end
        101010://SLT
        begin
            sel=3'b010;
        end
        endcase
    end
    endcase
end

endmodule

actividad10/BR.v
`timescale 1ns/1ns

module BR(
    input [4:0]ReadRegister1,
    input [4:0]ReadRegister2,
    input [4:0]WriteRegister,
    input RegEn,
    input [31:0]WriteData,
    output reg[31:0]ReadData1,//C
    output reg[31:0]ReadData2//C
);

reg [31:0]BR[0:310];

always @*
begin
    if(RegEn)
        begin
            BR[WriteRegister]=WriteData;
        end
    ReadData1=BR[ReadRegister1];
    ReadData2=BR[ReadRegister2];
end
initial 
begin
  $readmemb("Data.mem",BR);
end
endmodule

actividad10/UC.v
`timescale 1ns/1ns

module UC(
    input [5:0]op,
    output reg MemToReg,//C
    output reg Memtowrite,//C
    output reg [2:0]AluOp,//C
    output reg RegWrite//C
);

always @* 
begin
    case(op)
    6'b000000:
    begin
        MemToReg=0;
        Memtowrite=0;
        AluOp=3'b111;
        RegWrite=1;
    end
    endcase

end

endmodule

actividad10/datapath.v
`timescale 1ns/1ns

module datapath(
    input [31:0]intTr,
    output TR_ZF
);


//unidad de control
wire c_MemToReg,c_MemToWrite,c_RegWrite;
wire [2:0]c_AluOp;

//Banco de registros
wire [31:0]c_ReadData1;
wire [31:0]c_ReadData2;

//Alu Control
wire [2:0]c_Sel;

//Alu
wire [31:0]c_res;

//Memoria
wire c_EWR;
wire [31:0]c_ReadData;

//Mux21
wire [31:0]c_R;

UC UC_1(
    .op(intTr[31:26]),   
    .RegWrite(c_RegWrite),
    .Memtowrite(c_MemToWrite),
    .MemToReg(c_MemToReg),
    .AluOp(c_AluOp)
);

BR BR_1(
    .ReadRegister1(intTr[25:21]),
    .ReadRegister2(intTr[20:16]),
    .WriteRegister(intTr[15:11]),
    .RegEn(c_RegWrite), 
    .ReadData1(c_ReadData1),
    .ReadData2(c_ReadData2),
    .WriteData(c_R)
);

AluC AluC_1(
    .func(intTr[5:0]),
    .AluOp(c_AluOp),
    .sel(c_Sel)
);

Alu Alu_1(
    .op1(c_ReadData1),
    .op2(c_ReadData2),
    .sel(c_Sel),
    .zeroflag(TR_zf),
    .res(c_res)
);

Mem Mem_1(
    .Adress(c_res),
    .WD(c_ReadData2),
    .EWR(c_MemToWrite),
    .ReadData(c_ReadData)
);

mux21 mux21_1(
    .A(c_ReadData),
    .B(c_res),
    .sel(c_MemToReg),
    .R(c_R)
);

endmodule

actividad10/datapath_tb.v
`timescale 1ns/1ns


module datapath_tb;
    reg [31:0]intTr;
    wire TR_ZF;


datapath DUV(intTr,TR_ZF);

initial 
begin
    $dumpfile("datapath_tb.vcd");
    $dumpvars(0,datapath_tb);

    //ADD         
    #100;intTr=32'b00000000111010100100000000100000;//8
    #100;intTr=32'b00000010010010100100100000100000;//9
    
    //AND
    #100;intTr=32'b00000000010010110101000000100100;//10
    #100;intTr=32'b00000011111110100101100000100100;//11

    //SUB
    #100;intTr=32'b00000011110101000110000000100010;//12
    #100;intTr=32'b00000000011011110110100000100010;//13

    //OR
    #100;intTr=32'b00000010001001110111000000100101;//14
    #100;intTr=32'b00000010101010110111100000100101;//15

    //SLT
    #100;intTr=32'b00000010000101001000000000100101;//16
    #100;intTr=32'b00000011101000101000100000100101;//17
    $stop;
end

endmodule

actividad10/datapath_tb.vcd
$date
	Thu Nov 11 01:37:39 2021
$end
$version
	Icarus Verilog
$end
$timescale
	1ns
$end
$scope module datapath_tb $end
$var wire 1 ! TR_ZF $end
$var reg 32 " intTr [31:0] $end
$scope module DUV $end
$var wire 1 ! TR_ZF $end
$var wire 32 # intTr [31:0] $end
$var wire 32 $ c_res [31:0] $end
$var wire 3 % c_Sel [2:0] $end
$var wire 1 & c_RegWrite $end
$var wire 32 ' c_ReadData2 [31:0] $end
$var wire 32 ( c_ReadData1 [31:0] $end
$var wire 32 ) c_ReadData [31:0] $end
$var wire 32 * c_R [31:0] $end
$var wire 1 + c_MemToWrite $end
$var wire 1 , c_MemToReg $end
$var wire 3 - c_AluOp [2:0] $end
$var wire 1 . TR_zf $end
$scope module AluC_1 $end
$var wire 6 / func [5:0] $end
$var wire 3 0 AluOp [2:0] $end
$var reg 3 1 sel [2:0] $end
$upscope $end
$scope module Alu_1 $end
$var wire 3 2 sel [2:0] $end
$var wire 32 3 op2 [31:0] $end
$var wire 32 4 op1 [31:0] $end
$var reg 32 5 res [31:0] $end
$var reg 1 . zeroflag $end
$upscope $end
$scope module BR_1 $end
$var wire 5 6 ReadRegister1 [4:0] $end
$var wire 5 7 ReadRegister2 [4:0] $end
$var wire 5 8 WriteRegister [4:0] $end
$var wire 32 9 WriteData [31:0] $end
$var wire 1 & RegEn $end
$var reg 32 : ReadData1 [31:0] $end
$var reg 32 ; ReadData2 [31:0] $end
$upscope $end
$scope module Mem_1 $end
$var wire 32 < Adress [31:0] $end
$var wire 32 = WD [31:0] $end
$var wire 1 + EWR $end
$var reg 32 > ReadData [31:0] $end
$upscope $end
$scope module UC_1 $end
$var wire 6 ? op [5:0] $end
$var reg 3 @ AluOp [2:0] $end
$var reg 1 , MemToReg $end
$var reg 1 + Memtowrite $end
$var reg 1 & RegWrite $end
$upscope $end
$scope module mux21_1 $end
$var wire 32 A A [31:0] $end
$var wire 32 B B [31:0] $end
$var wire 1 , sel $end
$var reg 32 C R [31:0] $end
$upscope $end
$upscope $end
$upscope $end
$enddefinitions $end
#0
$dumpvars
bx C
bx B
bx A
bx @
bx ?
bx >
bx =
bx <
bx ;
bx :
bx 9
bx 8
bx 7
bx 6
bx 5
bx 4
bx 3
bx 2
bx 1
bx 0
bx /
x.
bx -
x,
x+
bx *
bx )
bx (
bx '
x&
bx %
bx $
bx #
bx "
z!
$end
#100
1&
b111 -
b111 0
b111 @
0+
0,
b1110010 '
b1110010 3
b1110010 ;
b1110010 =
b1000000 (
b1000000 4
b1000000 :
b0 ?
b111 6
b1010 7
b1000 8
b100000 /
b111010100100000000100000 "
b111010100100000000100000 #
#200
b0 (
b0 4
b0 :
b10010 6
b1001 8
b10010010100100100000100000 "
b10010010100100100000100000 #
#300
b1100011 '
b1100011 3
b1100011 ;
b1100011 =
b1110010 (
b1110010 4
b1110010 :
b10 6
b1011 7
b1010 8
b100100 /
b10010110101000000100100 "
b10010110101000000100100 #
#400
b0 '
b0 3
b0 ;
b0 =
b0 (
b0 4
b0 :
b11111 6
b11010 7
b1011 8
b11111110100101100000100100 "
b11111110100101100000100100 #
#500
b11110 6
b10100 7
b1100 8
b100010 /
b11110101000110000000100010 "
b11110101000110000000100010 #
#600
b1100001 (
b1100001 4
b1100001 :
b11 6
b1111 7
b1101 8
b11011110110100000100010 "
b11011110110100000100010 #
#700
b1000000 '
b1000000 3
b1000000 ;
b1000000 =
b0 (
b0 4
b0 :
b10001 6
b111 7
b1110 8
b100101 /
b10001001110111000000100101 "
b10001001110111000000100101 #
#800
bx '
bx 3
bx ;
bx =
b10101 6
b1011 7
b1111 8
b10101010110111100000100101 "
b10101010110111100000100101 #
#900
b0 '
b0 3
b0 ;
b0 =
bx (
bx 4
bx :
b10000 6
b10100 7
b10000 8
b10000101001000000000100101 "
b10000101001000000000100101 #
